gitconfig/__init__.py
MapGitConfig-1.1.dist-info/WHEEL
MapGitConfig-1.1.dist-info/DESCRIPTION.rst
MapGitConfig-1.1.dist-info/metadata.json
MapGitConfig-1.1.dist-info/RECORD
MapGitConfig-1.1.dist-info/top_level.txt
MapGitConfig-1.1.dist-info/METADATA
