Metadata-Version: 2.0
Name: MapGitConfig
Version: 1.1
Summary: Git Config Wrapper
Home-page: https://github.com/zalando/python-gitconfig
Author: Zalando
Author-email: joao.santos@zalando.de
License: UNKNOWN
Platform: UNKNOWN
Classifier: Programming Language :: Python
Classifier: Programming Language :: Python :: 2.7
Classifier: Programming Language :: Python :: 3.4
Classifier: Development Status :: 4 - Beta
Classifier: Intended Audience :: Developers
Classifier: Operating System :: OS Independent
Classifier: Topic :: Software Development :: Version Control
